testwizard/commands_powerswitch/GetPowerSwitchStatusCommand.py
testwizard/commands_powerswitch/GetPowerSwitchStatusResult.py
testwizard/commands_powerswitch/SwitchPowerCommand.py
testwizard/commands_powerswitch/SwitchPowerOffCommand.py
testwizard/commands_powerswitch/SwitchPowerOnCommand.py
testwizard/commands_powerswitch/__init__.py
testwizard.commands_powerswitch-3.8.1.dist-info/LICENSE.txt
testwizard.commands_powerswitch-3.8.1.dist-info/METADATA
testwizard.commands_powerswitch-3.8.1.dist-info/WHEEL
testwizard.commands_powerswitch-3.8.1.dist-info/top_level.txt
testwizard.commands_powerswitch-3.8.1.dist-info/RECORD
